tak/__init__.py
tak/main.py
tak-0.0.2.dist-info/LICENSE.md
tak-0.0.2.dist-info/METADATA
tak-0.0.2.dist-info/WHEEL
tak-0.0.2.dist-info/entry_points.txt
tak-0.0.2.dist-info/top_level.txt
tak-0.0.2.dist-info/RECORD
